joungwoo/__init__.py
joungwoo/jihoon.py
joungwoo_test-2.0.0.0.0.3.dist-info/METADATA
joungwoo_test-2.0.0.0.0.3.dist-info/WHEEL
joungwoo_test-2.0.0.0.0.3.dist-info/top_level.txt
joungwoo_test-2.0.0.0.0.3.dist-info/RECORD
